theborg/__init__.py
theborg/classifier.py
theborg/emulator.py
theborg/model.py
theborg/radam.py
theborg-1.0.7.dist-info/LICENSE
theborg-1.0.7.dist-info/METADATA
theborg-1.0.7.dist-info/WHEEL
theborg-1.0.7.dist-info/top_level.txt
theborg-1.0.7.dist-info/RECORD
